dragonfly/__init__.py
dragonfly/__main__.py
dragonfly/analysis.py
dragonfly/main.py
dragonfly/pie_chart.py
dragonfly/terminal.py
dragonfly/to_json_string.py
git_dragonfly-0.1.12.dist-info/METADATA
git_dragonfly-0.1.12.dist-info/WHEEL
git_dragonfly-0.1.12.dist-info/entry_points.txt
git_dragonfly-0.1.12.dist-info/top_level.txt
git_dragonfly-0.1.12.dist-info/RECORD
